sited_py/CHANGELOG.md
sited_py/README_CN.md
sited_py/README_EN.md
sited_py/__init__.py
sited_py/conf.py
sited_py/files/.gitignore
sited_py/lib/__init__.py
sited_py/lib/android_util_Log.py
sited_py/lib/main_res_raw_base64.js
sited_py/lib/main_res_raw_cheerio.js
sited_py/lib/main_res_raw_md5.js
sited_py/lib/main_res_raw_sha1.js
sited_py/lib/me_noear_db_DbContext.py
sited_py/lib/me_noear_utils_EncryptUtil.py
sited_py/lib/me_noear_utils_HttpUtil.py
sited_py/lib/mytool.py
sited_py/lib/noear_snacks.py
sited_py/lib/noear_snacks_OArray.py
sited_py/lib/noear_snacks_ONode.py
sited_py/lib/noear_snacks_ONodeBase.py
sited_py/lib/noear_snacks_ONodeType.py
sited_py/lib/noear_snacks_OObject.py
sited_py/lib/noear_snacks_OValue.py
sited_py/lib/noear_snacks_OValueType.py
sited_py/lib/org_noear_sited_DataBlock.py
sited_py/lib/org_noear_sited_DataContext.py
sited_py/lib/org_noear_sited_HttpMessage.py
sited_py/lib/org_noear_sited_JsEngine.py
sited_py/lib/org_noear_sited_SdAdapter.py
sited_py/lib/org_noear_sited_SdApi.py
sited_py/lib/org_noear_sited_SdAttributeList.py
sited_py/lib/org_noear_sited_SdExt.py
sited_py/lib/org_noear_sited_SdJscript.py
sited_py/lib/org_noear_sited_SdNode.py
sited_py/lib/org_noear_sited_SdNodeSet.py
sited_py/lib/org_noear_sited_SdSource.py
sited_py/lib/org_noear_sited_SdValue.py
sited_py/lib/org_noear_sited_Util.py
sited_py/lib/org_noear_sited___AsyncTag.py
sited_py/lib/org_noear_sited___CacheBlock.py
sited_py/lib/org_noear_sited___FileCache.py
sited_py/lib/org_noear_siteder_App.py
sited_py/lib/org_noear_siteder_Config.py
sited_py/lib/org_noear_siteder_dao_Session.py
sited_py/lib/org_noear_siteder_dao_Setting.py
sited_py/lib/org_noear_siteder_dao_SourceApi.py
sited_py/lib/org_noear_siteder_dao_db_BookNode.py
sited_py/lib/org_noear_siteder_dao_db_DbApi.py
sited_py/lib/org_noear_siteder_dao_db_SiteDbApi.py
sited_py/lib/org_noear_siteder_dao_engine_DdAdapter.py
sited_py/lib/org_noear_siteder_dao_engine_DdApi.py
sited_py/lib/org_noear_siteder_dao_engine_DdNode.py
sited_py-1.4.2.dist-info/LICENSE
sited_py-1.4.2.dist-info/METADATA
sited_py-1.4.2.dist-info/WHEEL
sited_py-1.4.2.dist-info/top_level.txt
sited_py-1.4.2.dist-info/RECORD
